README.rst
nose_pattern_exclude.py
setup.py
nose_pattern_exclude.egg-info/PKG-INFO
nose_pattern_exclude.egg-info/SOURCES.txt
nose_pattern_exclude.egg-info/dependency_links.txt
nose_pattern_exclude.egg-info/entry_points.txt
nose_pattern_exclude.egg-info/not-zip-safe
nose_pattern_exclude.egg-info/requires.txt
nose_pattern_exclude.egg-info/top_level.txt