Metadata-Version: 1.1
Name: nose-pattern-exclude
Version: 0.1.2
Summary: Exclude specific files and directories from nosetests runs.
Home-page: http://github.com/jkbr/nose-pattern-exclude
Author: Jakub Roztocil
Author-email: jakub@roztocil.name
License: BSD
Platform: UNKNOWN
Classifier: Intended Audience :: Developers
Classifier: Topic :: Software Development :: Testing
Classifier: Programming Language :: Python
